log78/__init__.py
log78/console_log78.py
log78/file_log78.py
log78/file_log_detail.py
log78/iconsole_log78.py
log78/ifile_log78.py
log78/ilog78.py
log78/iserver_log78.py
log78/kafka_server_log78.py
log78/log_entry.py
log78/logger78.py
log78/logstash_server_log78.py
log78/main.py
log78-2.1.4.dist-info/entry_points.txt
log78-2.1.4.dist-info/LICENSE
log78-2.1.4.dist-info/METADATA
log78-2.1.4.dist-info/WHEEL
log78-2.1.4.dist-info/RECORD
