Metadata-Version: 2.1
Name: log78
Version: 2.1.4
Summary: A flexible Python logging library supporting console, file, and server logging.
Home-page: https://github.com/www778878net/Log78
License: Apache-2.0
Keywords: logging,debug,development
Author: Frieda.Hu
Author-email: www778878net@189.cn
Requires-Python: >=3.9,<4.0
Classifier: License :: OSI Approved :: Apache Software License
Classifier: Programming Language :: Python
Classifier: Programming Language :: Python :: 3
Classifier: Programming Language :: Python :: 3.9
Classifier: Programming Language :: Python :: 3.10
Classifier: Programming Language :: Python :: 3.11
Classifier: Programming Language :: Python :: 3.12
Classifier: Programming Language :: Python :: 3.13
Requires-Dist: aiofiles (>=0.6.0,<0.7.0)
Requires-Dist: aiohttp (>=3.7.4,<4.0.0)
Requires-Dist: aiokafka (>=0.12.0,<0.13.0)
Requires-Dist: loguru (>=0.7.0,<0.8.0)
Project-URL: Documentation, https://github.com/www778878net/Log78
Project-URL: Repository, https://github.com/www778878net/Log78.git
